config_to_object/__init__.py
config_to_object/load_code.py
config_to_object-1.0.3.dist-info/METADATA
config_to_object-1.0.3.dist-info/WHEEL
config_to_object-1.0.3.dist-info/entry_points.txt
config_to_object-1.0.3.dist-info/top_level.txt
config_to_object-1.0.3.dist-info/RECORD
