Metadata-Version: 2.1
Name: config-to-object
Version: 1.0.3
Summary: A convinient .ini file to NamedTuple parser that supports type hinting
Home-page: https://github.com/yannikkellerde/config_to_object
Author: Yannik Keller
Author-email: yannik@kelnet.de
License: MIT
Platform: UNKNOWN
Classifier: License :: OSI Approved :: MIT License
Classifier: Programming Language :: Python
Classifier: Programming Language :: Python :: 3
